{
  "groups": [
    {
      "title": "Default Content",
      "id": "default",
      "components": [
        {
          "title": "Text",
          "id": "text",
          "plugins": {
            "xwalk": {
              "page": {
                "resourceType": "core/franklin/components/text/v1/text",
                "template": {}
              }
            }
          }
        },
        {
          "title": "Title",
          "id": "title",
          "plugins": {
            "xwalk": {
              "page": {
                "resourceType": "core/franklin/components/title/v1/title",
                "template": {}
              }
            }
          }
        },
        {
          "title": "Image",
          "id": "image",
          "plugins": {
            "xwalk": {
              "page": {
                "resourceType": "core/franklin/components/image/v1/image",
                "template": {}
              }
            }
          }
        },
        {
          "title": "Button",
          "id": "button",
          "plugins": {
            "xwalk": {
              "page": {
                "resourceType": "core/franklin/components/button/v1/button",
                "template": {}
              }
            }
          }
        }
      ]
    },
    {
      "title": "Containers",
      "id": "sections",
      "components": [
        {
          "title": "Section",
          "id": "section",
          "plugins": {
            "xwalk": {
              "page": {
                "resourceType": "core/franklin/components/section/v1/section",
                "template": {
                  "name": "Section",
                  "model": "section",
                  "style": "default",
                  "filter": "section"
                }
              }
            }
          }
        }
      ]
    },
    {
      "title": "Blocks",
      "id": "blocks",
      "components": [
        {
          "title": "Columns",
          "id": "columns",
          "plugins": {
            "xwalk": {
              "page": {
                "resourceType": "core/franklin/components/columns/v1/columns",
                "template": {
                  "columns": "2",
                  "rows": "1"
                }
              }
            }
          }
        },
        {
          "title": "Hero",
          "id": "hero",
          "plugins": {
            "xwalk": {
              "page": {
                "resourceType": "core/franklin/components/block/v1/block",
                "template": {
                  "name": "Hero",
                  "model": "hero"
                }
              }
            }
          }
        },
        {
          "title": "Cards",
          "id": "cards",
          "plugins": {
            "xwalk": {
              "page": {
                "resourceType": "core/franklin/components/block/v1/block",
                "template": {
                  "name": "Cards",
                  "filter": "cards"
                }
              }
            }
          }
        },
        {
          "title": "Card",
          "id": "card",
          "plugins": {
            "xwalk": {
              "page": {
                "resourceType": "core/franklin/components/block/v1/block/item",
                "template": {
                  "name": "Card",
                  "model": "card"
                }
              }
            }
          }
        },
        {
          "title": "Data Cards",
          "id": "data-cards",
          "plugins": {
            "xwalk": {
              "page": {
                "resourceType": "core/franklin/components/block/v1/block",
                "template": {
                  "name": "Data Cards",
                  "model": "data-cards",
                  "filter": "data-cards",
                  "title": "<p><strong>Data</strong> for Development</p>",
                  "description": "<p>Essential data to guide decisions, monitor progress, and evaluate impacts</p>",
                  "additional-text": "<p>Explore by focus area</p>"
                }
              }
            }
          }
        },
        {
          "title": "Data Card",
          "id": "data-card",
          "plugins": {
            "xwalk": {
              "page": {
                "resourceType": "core/franklin/components/block/v1/block/item",
                "template": {
                  "name": "Data Card",
                  "model": "data-card"
                }
              }
            }
          }
        },
        {
          "title": "News Card",
          "id": "news-card",
          "plugins": {
            "xwalk": {
              "page": {
                "resourceType": "core/franklin/components/block/v1/block/item",
                "template": {
                  "name": "News Card",
                  "model": "news-card"
                }
              }
            }
          }
        },
        {
          "title": "Curated Cards",
          "id": "curated-cards",
          "plugins": {
            "xwalk": {
              "page": {
                "resourceType": "core/franklin/components/block/v1/block",
                "template": {
                  "name": "Curated Cards",
                  "filter": "curated-cards",
                  "item1": {
                    "sling:resourceType": "core/franklin/components/block/v1/block/item",
                    "name": "Curated Card",
                    "model": "curated-card",
                    "curated-card-image": "/content/dam/world-bank/sample/3000x2400.svg",
                    "curated-card-tags": "world-bank:content-type/event",
                    "curated-card-title": "Curated Card Title",
                    "curated-card-description": "Card Description",
                    "curated-card-link": "/content/world-bank/global/en"
                  },
                  "item2": {
                    "sling:resourceType": "core/franklin/components/block/v1/block/item",
                    "name": "Curated Card",
                    "model": "curated-card",
                    "curated-card-image": "/content/dam/world-bank/sample/799x533.svg",
                    "curated-card-tags": "world-bank:content-type/event",
                    "curated-card-title": "Curated Card Title",
                    "curated-card-description": "Card Description",
                    "curated-card-link": "/content/world-bank/global/en"
                  },
                  "item3": {
                    "sling:resourceType": "core/franklin/components/block/v1/block/item",
                    "name": "Curated Card",
                    "model": "curated-card",
                    "curated-card-image": "/content/dam/world-bank/sample/799x533.svg",
                    "curated-card-tags": "world-bank:content-type/feature-story",
                    "curated-card-title": "Curated Card Title",
                    "curated-card-description": "Card Description",
                    "curated-card-link": "/content/world-bank/global/en"
                  },
                  "item4": {
                    "sling:resourceType": "core/franklin/components/block/v1/block/item",
                    "curated-card-name": "Curated Card",
                    "model": "curated-card",
                    "curated-card-image": "/content/dam/world-bank/sample/799x533.svg",
                    "curated-card-tags": "evworld-bank:content-type/event",
                    "curated-card-title": "Curated Card Title",
                    "curated-card-description": "Card Description",
                    "curated-card-link": "/content/world-bank/global/en"
                  }
                }
              }
            }
          }
        },
        {
          "title": "Curated Card",
          "id": "curated-card",
          "plugins": {
            "xwalk": {
              "page": {
                "resourceType": "core/franklin/components/block/v1/block/item",
                "template": {
                  "name": "Curated Card",
                  "model": "curated-card"
                }
              }
            }
          }
        },
        {
          "title": "Explore Cards",
          "id": "explore-cards",
          "plugins": {
            "xwalk": {
              "page": {
                "resourceType": "core/franklin/components/block/v1/block",
                "template": {
                  "name": "Explore Cards",
                  "model": "explore-cards",
                  "filter": "explore-cards",
                  "title": "<p>Explore Development Stories <strong>From Around the World</strong></p>",
                  "item1": {
                    "sling:resourceType": "core/franklin/components/block/v1/block/item",
                    "name": "Explore Card",
                    "model": "explore-card",
                    "fileReference": "/content/dam/world-bank/sample/placeholder-black.png",
                    "alt": "Alt text",
                    "title": "Green Jobs. Learn What They Are. And Why We’re Invested.",
                    "link": "/content/world-bank/global/en",
                    "content-type": "world-bank:content-type/audio",
                    "story-type": "world-bank:story-type/immersive-stories"
                  },
                  "item2": {
                    "sling:resourceType": "core/franklin/components/block/v1/block/item",
                    "name": "Explore Card",
                    "model": "explore-card",
                    "fileReference": "/content/dam/world-bank/sample/placeholder-black.png",
                    "alt": "Alt text",
                    "title": "Inside Somalia: Signs of Hope on the Road to Recovery.",
                    "link": "/content/world-bank/global/en",
                    "content-type": "world-bank:content-type/article",
                    "story-type": "world-bank:story-type/the-development-podcast"
                  },
                  "item3": {
                    "sling:resourceType": "core/franklin/components/block/v1/block/item",
                    "name": "Explore Card",
                    "model": "explore-card",
                    "fileReference": "/content/dam/world-bank/sample/placeholder-black.png",
                    "alt": "Alt text",
                    "title": "Discover the Link Between Plastic Pollution and Poverty.",
                    "link": "/content/world-bank/global/en",
                    "content-type": "world-bank:content-type/video",
                    "story-type": "world-bank:story-type/expert-answers"
                  }
                }
              }
            }
          }
        },
        {
          "title": "Explore Card",
          "id": "explore-card",
          "plugins": {
            "xwalk": {
              "page": {
                "resourceType": "core/franklin/components/block/v1/block/item",
                "template": {
                  "name": "Explore Card",
                  "model": "explore-card"
                }
              }
            }
          }
        },
        {
          "title": "Mini Cards",
          "id": "mini-cards",
          "plugins": {
            "xwalk": {
              "page": {
                "resourceType": "core/franklin/components/block/v1/block",
                "template": {
                  "name": "Mini Cards",
                  "filter": "mini-cards",
                  "model": "mini-cards",
                  "mini-cards-heading": "<p>The Heading for <strong>Mini Cards Block</strong></p>",
                  "item1": {
                    "sling:resourceType": "core/franklin/components/block/v1/block/item",
                    "name": "Mini Card",
                    "model": "mini-card",
                    "mini-card-image": "/content/dam/world-bank/sample/placeholder-black.png",
                    "mini-card-tag": "world-bank:content-type/event",
                    "mini-card-title": "Mini Card Title",
                    "mini-card-date": "July 18",
                    "mini-card-time": "8:30 AM",
                    "mini-card-link": "/content/world-bank/global/en",
                    "mini-card-location": "city, country"
                  },
                  "item2": {
                    "sling:resourceType": "core/franklin/components/block/v1/block/item",
                    "name": "Mini Card",
                    "model": "mini-card",
                    "mini-card-image": "/content/dam/world-bank/sample/placeholder-black.png",
                    "mini-card-tag": "world-bank:content-type/event",
                    "mini-card-title": "Mini Card Title",
                    "mini-card-date": "July 18",
                    "mini-card-time": "",
                    "mini-card-link": "/content/world-bank/global/en"
                  },
                  "item3": {
                    "sling:resourceType": "core/franklin/components/block/v1/block/item",
                    "name": "Mini Card",
                    "model": "mini-card",
                    "mini-card-image": "/content/dam/world-bank/sample/placeholder-black.png",
                    "mini-card-tag": "world-bank:content-type/event",
                    "mini-card-title": "Mini Card Title",
                    "mini-card-date": "July 18",
                    "mini-card-time": "",
                    "mini-card-link": "/content/world-bank/global/en"
                  }
                }
              }
            }
          }
        },
        {
          "title": "Mini Card",
          "id": "mini-card",
          "plugins": {
            "xwalk": {
              "page": {
                "resourceType": "core/franklin/components/block/v1/block/item",
                "template": {
                  "name": "Mini Card",
                  "model": "mini-card"
                }
              }
            }
          }
        },
        {
          "title": "Research Publications Cards",
          "id": "research-publications-cards",
          "plugins": {
            "xwalk": {
              "page": {
                "resourceType": "core/franklin/components/block/v1/block",
                "template": {
                  "name": "Research Publications Cards",
                  "model": "research-publications-cards",
                  "filter": "research-publications-cards",
                  "title": "<p>&nbsp;<strong>Research</strong> & Publications</p>",
                  "buttontext": "More Research & Publications",
                  "buttonlink": "https://www.worldbank.org",
                  "item1": {
                    "sling:resourceType": "core/franklin/components/block/v1/block/item",
                    "name": "Research Publications Card",
                    "model": "research-publications-card",
                    "image": "/content/dam/world-bank/sample/placeholder-black.png",
                    "alt": "Global Economy Set for Weakest Showing in 30 Years",
                    "title": "Global Economy Set for Weakest Showing in 30 Years",
                    "description": "Find global economic outlook, regional outlooks and special topics in this twice-a-year flagship publication.",
                    "href": "https://www.worldbank.org",
                    "buttontext": "Read Full Report",
                    "buttonlink": "https://www.worldbank.org"
                  },
                  "item2": {
                    "sling:resourceType": "core/franklin/components/block/v1/block/item",
                    "name": "Research Publications Card",
                    "model": "research-publications-card",
                    "image": "/content/dam/world-bank/sample/placeholder-black.png",
                    "alt": "Bend the Emissions Curve",
                    "title": "Bend the Emissions Curve",
                    "description": "State and Trends of Carbon Pricing 2024 helps inform, influence and incentivize better policies for a warming world.",
                    "href": "https://www.worldbank.org",
                    "buttontext": "Read Full Report",
                    "buttonlink": "https://www.worldbank.org"
                  }
                }
              }
            }
          }
        },
        {
          "title": "Research Publications Card",
          "id": "research-publications-card",
          "plugins": {
            "xwalk": {
              "page": {
                "resourceType": "core/franklin/components/block/v1/block/item",
                "template": {
                  "name": "Research Publications Card",
                  "model": "research-publications-card"
                }
              }
            }
          }
        },
        {
          "title": "Signup",
          "id": "signup",
          "plugins": {
            "xwalk": {
              "page": {
                "resourceType": "core/franklin/components/block/v1/block",
                "template": {
                  "name": "Signup",
                  "filter": "signup"
                }
              }
            }
          }
        },
        {
          "title": "Teaser",
          "id": "teaser",
          "plugins": {
            "xwalk": {
              "page": {
                "resourceType": "core/franklin/components/block/v1/block",
                "template": {
                  "name": "teaser",
                  "model": "teaser",
                  "key-value": true
                }
              }
            }
          }
        },
        {
          "title": "Live Now",
          "id": "live-now",
          "plugins": {
            "xwalk": {
              "page": {
                "resourceType": "core/franklin/components/block/v1/block",
                "template": {
                  "name": "live-now",
                  "model": "live-now",
                  "key-value": true
                }
              }
            }
          }
        },
        {
          "title": "Tabs",
          "id": "tabs",
          "plugins": {
            "xwalk": {
              "page": {
                "resourceType": "core/franklin/components/block/v1/block",
                "template": {
                  "name": "Tabs",
                  "model": "tabs",
                  "filter": "tab",
                  "item1": {
                    "sling:resourceType": "core/franklin/components/block/v1/block/item",
                    "name": "Tab",
                    "model": "tab",
                    "title": "Tab"
                  }
                }
              }
            }
          }
        },
        {
          "title": "Tab",
          "id": "tab",
          "plugins": {
            "xwalk": {
              "page": {
                "resourceType": "core/franklin/components/block/v1/block/item",
                "template": {
                  "name": "Tab",
                  "model": "tab",
                  "title": "Tab"
                }
              }
            }
          }
        },
        {
          "title": "Priority List",
          "id": "priority-list",
          "plugins": {
            "xwalk": {
              "page": {
                "resourceType": "core/franklin/components/block/v1/block",
                "template": {
                  "name": "Priority List",
                  "model": "priority-list",
                  "filter": "priority-list"
                }
              }
            }
          }
        },
        {
          "title": "Priority Item",
          "id": "priority-item",
          "plugins": {
            "xwalk": {
              "page": {
                "resourceType": "core/franklin/components/block/v1/block/item",
                "template": {
                  "name": "Priority Item",
                  "model": "priority-item"
                }
              }
            }
          }
        },
        {
          "title": "Leaders List",
          "id": "leaders-list",
          "plugins": {
            "xwalk": {
              "page": {
                "resourceType": "core/franklin/components/block/v1/block",
                "template": {
                  "name": "Leaders List",
                  "model": "leaders-list"
                }
              }
            }
          }
        },
        {
          "title": "Bio Detail",
          "id": "bio-detail",
          "plugins": {
            "xwalk": {
              "page": {
                "resourceType": "core/franklin/components/block/v1/block",
                "template": {
                  "name": "Bio Detail",
                  "model": "bio-detail"
                }
              }
            }
          }
        }     
      ]
    }
  ]
}
